streaminghub_pydfds/__init__.py
streaminghub_pydfds/const.py
streaminghub_pydfds/loader.py
streaminghub_pydfds/parser.py
streaminghub_pydfds/readers.py
streaminghub_pydfds/typing.py
streaminghub_pydfds/url.py
streaminghub_pydfds/util.py
streaminghub_pydfds-0.1.40.dist-info/LICENSE
streaminghub_pydfds-0.1.40.dist-info/METADATA
streaminghub_pydfds-0.1.40.dist-info/WHEEL
streaminghub_pydfds-0.1.40.dist-info/top_level.txt
streaminghub_pydfds-0.1.40.dist-info/RECORD
