Metadata-Version: 2.1
Name: streaminghub-pydfds
Version: 0.1.40
Summary: Parser for Data Flow Description Schema (DFDS) metadata
Author-email: Yasith Jayawardana <yasith@cs.odu.edu>
License: Copyright (c) 2024 Old Dominion University
Project-URL: homepage, https://github.com/nirdslab/streaminghub/tree/master/pydfds
Keywords: dfds,metadata,parser
Classifier: Programming Language :: Python :: 3
Classifier: License :: OSI Approved :: MIT License
Classifier: Operating System :: OS Independent
Requires-Python: >=3.10
License-File: LICENSE
Requires-Dist: numpy
Requires-Dist: jsonschema
Requires-Dist: pydantic
Requires-Dist: h5py
Requires-Dist: parse
Requires-Dist: pandas
Provides-Extra: dev
Requires-Dist: black; extra == "dev"
Requires-Dist: build; extra == "dev"
Requires-Dist: twine; extra == "dev"
Requires-Dist: bumpver; extra == "dev"
Requires-Dist: isort; extra == "dev"
Requires-Dist: pip-tools; extra == "dev"
Requires-Dist: pytest; extra == "dev"
